rethink/.env.local
rethink/__init__.py
rethink/_version.py
rethink/application.py
rethink/config.py
rethink/const.py
rethink/logger.py
rethink/regex.py
rethink/run.py
rethink/utils.py
rethink/controllers/__init__.py
rethink/controllers/auth.py
rethink/controllers/email.py
rethink/controllers/oauth.py
rethink/controllers/plugin.py
rethink/controllers/utils.py
rethink/controllers/files/__init__.py
rethink/controllers/files/upload_files.py
rethink/controllers/node/__init__.py
rethink/controllers/node/node_ops.py
rethink/controllers/node/trash_ops.py
rethink/controllers/schemas/__init__.py
rethink/controllers/schemas/base.py
rethink/controllers/schemas/files.py
rethink/controllers/schemas/node.py
rethink/controllers/schemas/oauth.py
rethink/controllers/schemas/plugin.py
rethink/controllers/schemas/search.py
rethink/controllers/schemas/user.py
rethink/controllers/search/__init__.py
rethink/controllers/search/node_search.py
rethink/controllers/user/__init__.py
rethink/controllers/user/password.py
rethink/controllers/user/user_ops.py
rethink/controllers/verify/__init__.py
rethink/controllers/verify/v_captcha.py
rethink/core/__init__.py
rethink/core/search.py
rethink/core/user.py
rethink/core/files/__init__.py
rethink/core/files/get.py
rethink/core/files/saver.py
rethink/core/files/upload.py
rethink/core/files/importing/__init__.py
rethink/core/files/importing/async_tasks/__init__.py
rethink/core/files/importing/async_tasks/utils.py
rethink/core/files/importing/async_tasks/obsidian/__init__.py
rethink/core/files/importing/async_tasks/obsidian/ops.py
rethink/core/files/importing/async_tasks/obsidian/task.py
rethink/core/files/importing/async_tasks/text/__init__.py
rethink/core/files/importing/async_tasks/text/task.py
rethink/core/files/importing/sync_tasks/__init__.py
rethink/core/files/importing/sync_tasks/editor.py
rethink/core/node/__init__.py
rethink/core/node/backup.py
rethink/core/node/node.py
rethink/core/node/node_utils.py
rethink/core/verify/__init__.py
rethink_note-0.2.4.dist-info/LICENSE
rethink_note-0.2.4.dist-info/METADATA
rethink_note-0.2.4.dist-info/WHEEL
rethink_note-0.2.4.dist-info/top_level.txt
rethink_note-0.2.4.dist-info/RECORD
