Metadata-Version: 2.1
Name: rethink-note
Version: 0.2.4
Summary: note taking app
Home-page: https://github.com/MorvanZhou/rethink
Author: MorvanZhou
Author-email: morvanzhou@hotmail.com
Project-URL: Bug Tracker, https://github.com/MorvanZhou/rethink/issues
Project-URL: Source, https://github.com/MorvanZhou/rethink
Classifier: Programming Language :: Python :: 3
Classifier: Programming Language :: Python :: 3 :: Only
Classifier: Programming Language :: Python :: 3.8
Classifier: Programming Language :: Python :: 3.9
Classifier: Programming Language :: Python :: 3.10
Classifier: Programming Language :: Python :: 3.11
Classifier: License :: OSI Approved :: MIT License
Classifier: Operating System :: OS Independent
Requires-Python: >=3.8
License-File: LICENSE
Requires-Dist: fastapi >=0.95.2
Requires-Dist: pydantic[email] >=2.1.1
Requires-Dist: pydantic-settings >=2.0.3
Requires-Dist: uvicorn[standard]
Requires-Dist: pyjwt[crypto] >=2.8.0
Requires-Dist: bcrypt >=4.0.1
Requires-Dist: sortedcontainers <3.0,>=2.3
Requires-Dist: pymongo >=4.6.0
Requires-Dist: markdown >=3.4.4
Requires-Dist: oauthlib >=3.2.2
Requires-Dist: httpx >=0.25.0
Requires-Dist: captcha >=0.5.0
Requires-Dist: python-multipart >=0.0.6
Requires-Dist: cos-python-sdk-v5 >=1.9.26
Requires-Dist: numpy >=1.24.4
Requires-Dist: whoosh >=2.7.4
Requires-Dist: jieba >=0.42.1
Requires-Dist: starlette >=0.27.0
Requires-Dist: jinja2 >=3.1.3
Provides-Extra: build
Requires-Dist: tox ==3.24.3 ; extra == 'build'
Requires-Dist: tox-conda ; extra == 'build'
Requires-Dist: build ; extra == 'build'
Requires-Dist: twine ; extra == 'build'
Requires-Dist: pylint ; extra == 'build'
Provides-Extra: remote
Requires-Dist: motor >=3.3.2 ; extra == 'remote'
Requires-Dist: elasticsearch[async] ~=8.11.0 ; extra == 'remote'
